Workbook

Sheet Assumptions - Revenue
A2: Assumptions - Revenue, License Rates, Subscribers
G3: Subscribers at End of Period
A4: * Shaded assumptions can be edited | G4: Year 1 Ramp Up
E5: Initial Rate / Month | G5: Sept | H5: Oct | I5: Nov | J5: Dec | K5: Jan | L5: Feb | M5: Mar | N5: Apr | O5: May | P5: Jun | Q5: Jul | R5: Aug | S5: Total Yr 1 | T5: Year 2 | U5: Year 3 | V5: Year 4 | W5: Year 5
B7: Individual License | E7: 100 | G7: 0 | H7: 0 | I7: 0 | J7: 0 | K7: 0 | L7: 0 | M7: 0 | N7: 35 | O7: 100 | P7: 250 | Q7: 300 | R7: 450 | S7: =R7 -> 450 | T7: 800 | U7: 1000 | V7: 1250 | W7: 1500
B8: Individual Plus Five Licenses | E8: 350 | G8: 0 | H8: 0 | I8: 0 | J8: 0 | K8: 0 | L8: 0 | M8: 0 | N8: 5 | O8: 8 | P8: 20 | Q8: 25 | R8: 50 | S8: =R8 -> 50 | T8: 100 | U8: 140 | V8: 150 | W8: 350
B9: Individual Plus Ten Licenses | E9: 600 | G9: 0 | H9: 0 | I9: 0 | J9: 0 | K9: 0 | L9: 0 | M9: 0 | N9: 1 | O9: 3 | P9: 10 | Q9: 15 | R9: 25 | S9: =R9 -> 25 | T9: 30 | U9: 40 | V9: 75 | W9: 100
B10: Unlimited | E10: 1250 | G10: 0 | H10: 0 | I10: 0 | J10: 0 | K10: 0 | L10: 0 | M10: 0 | N10: 0 | O10: 1 | P10: 3 | Q10: 5 | R10: 8 | S10: =R10 -> 8 | T10: 10 | U10: 12 | V10: 30 | W10: 50
B12: Total Subscribers | G12: =SUM(G7:G10) -> 0 | H12: =SUM(H7:H10) -> 0 | I12: =SUM(I7:I10) -> 0 | J12: =SUM(J7:J10) -> 0 | K12: =SUM(K7:K10) -> 0 | L12: =SUM(L7:L10) -> 0 | M12: =SUM(M7:M10) -> 0 | N12: =SUM(N7:N10) -> 41 | ... W12: =SUM(W7:W10) -> 2000
B14: Subscription Inflation Rate
B15: Year 1 | C15: 0
B16: Year 2 | C16: 0
B17: Year 3 | C17: 0.1
B18: Year 4 | C18: 0
B19: Year 5 | C19: 0.1
B21: Annual Churn on Subscriptions | C21: The model does not currently calculate any results based on these assumptions.
B23: Marketing Subscriber Conversion Rate
B25: Organic Traffic Subscriber Conversion Rate
B27: Total Market
B29: Market Share
B32: Calculation Tables | E32: Year 1 | F32: Year 2 | G32: Year 3 | H32: Year 4 | I32: Year 5
B33: Monthly License Rate with Inflation Rates
B34: Individual License | E34: =E7*(1+C$15) -> 100 | F34: =E34*(1+$C$16) -> 100 | G34: =F34*(1+$C$17) -> 110 | H34: =G34*(1+$C$18) -> 110 | I34: =H34*(1+$C$19) -> 121
B35: Individual Plus Five Licenses | E35: =E8*(1+C$15) -> 350 | F35: =E35*(1+$C$16) -> 350 | G35: =F35*(1+$C$17) -> 385 | H35: =G35*(1+$C$18) -> 385 | I35: =H35*(1+$C$19) -> 423.5
B36: Individual Plus Ten Licenses | E36: =E9*(1+C$15) -> 600 | F36: =E36*(1+$C$16) -> 600 | G36: =F36*(1+$C$17) -> 660 | H36: =G36*(1+$C$18) -> 660 | I36: =H36*(1+$C$19) -> 726
B37: Unlimited | E37: =E10*(1+C$15) -> 1250 | F37: =E37*(1+$C$16) -> 1250 | G37: =F37*(1+$C$17) -> 1375 | H37: =G37*(1+$C$18) -> 1375 | I37: =H37*(1+$C$19) -> 1512.5

Sheet Assumptions - Personnel
A2: Assumptions - Personnel, Contract Labor, Salary Expense
A5: * Shaded assumptions can be edited | G5: Year 1 Ramp Up
G6: Sept | H6: Oct | I6: Nov | J6: Dec | K6: Jan | L6: Feb | M6: Mar | N6: Apr | O6: May | P6: Jun | Q6: Jul | R6: Aug | S6: Total Yr 1 | T6: Year 2 | U6: Year 3 | V6: Year 4 | W6: Year 5
B7: Contract Labor Expense
B8: Technology Development / Customer Service | G8: 4166 | H8: 4166 | I8: 4166 | J8: 4166 | K8: 4166 | L8: 4166 | M8: 4166 | N8: 4166 | O8: 4166 | P8: 4166 | Q8: 4166 | R8: 4174 | S8: =SUM(G8:R8) -> 50000 | T8: 50000 | U8: 50000 | V8: 50000 | W8: 50000
B9: Sales | S9: =SUM(G9:R9) -> 0 | T9: 50000 | U9: 150000 | V9: 200000 | W9: 250000
B10: Data Collection | S10: =SUM(G10:R10) -> 0 | T10: 50000 | U10: 50000 | V10: 50000 | W10: 50000
B12: Total Contract Labor Expense | G12: =SUM(G8:G10) -> 4166 | H12: =SUM(H8:H10) -> 4166 | I12: =SUM(I8:I10) -> 4166 | J12: =SUM(J8:J10) -> 4166 | K12: =SUM(K8:K10) -> 4166 | L12: =SUM(L8:L10) -> 4166 | M12: =SUM(M8:M10) -> 4166 | N12: =SUM(N8:N10) -> 4166 | ... W12: =SUM(W8:W10) -> 350000
B16: Employee Salary Expense
B17: CEO | G17: 6250 | H17: 6250 | I17: 6250 | J17: 6250 | K17: 6250 | L17: 6250 | M17: 6250 | N17: 6250 | O17: 6250 | P17: 6250 | Q17: 6250 | R17: 6250 | S17: =SUM(G17:R17) -> 75000 | T17: 125000 | U17: 150000 | V17: 175000 | W17: 200000
B18: COO | G18: 5000 | H18: 5000 | I18: 5000 | J18: 5000 | K18: 5000 | L18: 5000 | M18: 5000 | N18: 5000 | O18: 5000 | P18: 5000 | Q18: 5000 | R18: 5000 | S18: =SUM(G18:R18) -> 60000 | T18: 100000 | U18: 125000 | V18: 150000 | W18: 175000
B19: CSO | G19: 5000 | H19: 5000 | I19: 5000 | J19: 5000 | K19: 5000 | L19: 5000 | M19: 5000 | N19: 5000 | O19: 5000 | P19: 5000 | Q19: 5000 | R19: 5000 | S19: =SUM(G19:R19) -> 60000 | T19: 100000 | U19: 125000 | V19: 150000 | W19: 175000
B20: Administrative Support | S20: =SUM(G20:R20) -> 0
B22: Total Employee Salary Expense | G22: =SUM(G17:G20) -> 16250 | H22: =SUM(H17:H20) -> 16250 | I22: =SUM(I17:I20) -> 16250 | J22: =SUM(J17:J20) -> 16250 | K22: =SUM(K17:K20) -> 16250 | L22: =SUM(L17:L20) -> 16250 | M22: =SUM(M17:M20) -> 16250 | N22: =SUM(N17:N20) -> 16250 | ... W22: =SUM(W17:W20) -> 550000
B25: Fringe Benefit Rate | C25: 0.22

Sheet Assumptions - Non-Personnel Exp
A2: Assumptions - Non-Personnel Expenses
A5: * Shaded assumptions can be edited | G5: Year 1 Ramp Up
G6: Sept | H6: Oct | I6: Nov | J6: Dec | K6: Jan | L6: Feb | M6: Mar | N6: Apr | O6: May | P6: Jun | Q6: Jul | R6: Aug | S6: Total Yr 1 | T6: Year 2 | U6: Year 3 | V6: Year 4 | W6: Year 5
B8: Technology Engineering & Development - Capitalized
B9: Initial | G9: 0 | H9: 50000 | I9: 50000 | J9: 50000 | K9: 50000 | L9: 50000 | M9: 50000 | N9: 50000 | S9: =SUM(G9:R9) -> 350000 | T9: 150000 | U9: 50000 | V9: 50000
B10: Local Government Addition | S10: =SUM(G10:R10) -> 0 | U10: 150000 | V10: 50000
B11: Other States Addition | S11: =SUM(G11:R11) -> 0 | W11: 350000
B13: Total Technology Engineering & Development - Capitalized | G13: =SUM(G9:G11) -> 0 | H13: =SUM(H9:H11) -> 50000 | I13: =SUM(I9:I11) -> 50000 | J13: =SUM(J9:J11) -> 50000 | K13: =SUM(K9:K11) -> 50000 | L13: =SUM(L9:L11) -> 50000 | M13: =SUM(M9:M11) -> 50000 | N13: =SUM(N9:N11) -> 50000 | ... W13: =SUM(W9:W11) -> 350000
B15: Technology Maintenance - Operating Expense
B18: Marketing/Advertising | G18: 0 | H18: 0 | I18: 2500 | J18: 4500 | K18: 8500 | L18: 8500 | M18: 8500 | N18: 8500 | O18: 8500 | P18: 8500 | Q18: 8500 | R18: 8500 | S18: =SUM(G18:R18) -> 75000 | T18: 75000 | U18: 100000 | V18: 100000 | W18: 150000
B21: Website Hosting, AWS Database, Misc Saas Fees | G21: 845 | H21: 845 | I21: 845 | J21: 845 | K21: 845 | L21: 845 | M21: 845 | N21: 845 | O21: 845 | P21: 845 | Q21: 845 | R21: 845 | S21: =SUM(G21:R21) -> 10140 | T21: 10140 | U21: 10140 | V21: 10140 | W21: 10140
B24: Other Expenses
B25: CRM (Hubspot) | G25: 50 | H25: 50 | I25: 50 | J25: 50 | K25: 50 | L25: 50 | M25: 50 | N25: 50 | O25: 50 | P25: 50 | Q25: 50 | R25: 50 | S25: =SUM(G25:R25) -> 600 | T25: 600 | U25: 600 | V25: 600 | W25: 600
B26: Travel, events | O26: 1000 | P26: 1000 | Q26: 1000 | R26: 1000 | S26: =SUM(G26:R26) -> 4000 | T26: 10000 | U26: 10000 | V26: 25000 | W26: 25000
B27: Legal | G27: 15000 | H27: 3000 | I27: 0 | J27: 0 | K27: 0 | S27: =SUM(G27:R27) -> 18000
S28: =SUM(G28:R28) -> 0
B30: Total Other Expenses | G30: =SUM(G25:G28) -> 15050 | H30: =SUM(H25:H28) -> 3050 | I30: =SUM(I25:I28) -> 50 | J30: =SUM(J25:J28) -> 50 | K30: =SUM(K25:K28) -> 50 | L30: =SUM(L25:L28) -> 50 | M30: =SUM(M25:M28) -> 50 | N30: =SUM(N25:N28) -> 50 | ... R30: =SUM(R25:R28) -> 1050 | S30: =SUM(G30:R30) -> 22600 | T30: =SUM(T25:T28) -> 10600 | U30: =SUM(U25:U28) -> 10600 | V30: =SUM(V25:V28) -> 25600 | W30: =SUM(W25:W28) -> 25600

Sheet Assumpt.-Equity & Bal Sheet 
A2: Assumptions - Equity & Balance Sheet Assumptions
G4: Equity Distribution at End of Period
A5: * Shaded assumptions can be edited | G5: Year 1 Ramp Up
G6: Sept | H6: Oct | I6: Nov | J6: Dec | K6: Jan | L6: Feb | M6: Mar | N6: Apr | O6: May | P6: Jun | Q6: Jul | R6: Aug | S6: Year 1 | T6: Year 2 | U6: Year 3 | V6: Year 4 | W6: Year 5
B8: Equity Ownership
B9: Owner A | G9: 0.4 | H9: 0.4 | I9: 0.4 | J9: 0.37 | K9: 0.37 | L9: 0.37 | M9: 0.37 | N9: 0.37 | O9: 0.37 | P9: 0.37 | Q9: 0.37 | R9: 0.37 | S9: =R9 -> 0.37 | T9: 0.37 | U9: 0.37 | V9: 0.37 | W9: 0.39
B10: Owner B | G10: 0.3 | H10: 0.3 | I10: 0.3 | J10: 0.285 | K10: 0.285 | L10: 0.285 | M10: 0.285 | N10: 0.285 | O10: 0.285 | P10: 0.285 | Q10: 0.285 | R10: 0.285 | S10: =R10 -> 0.285 | T10: 0.285 | U10: 0.285 | V10: 0.285 | W10: 0.29
B11: Owner C | G11: 0.3 | H11: 0.3 | I11: 0.3 | J11: 0.285 | K11: 0.285 | L11: 0.285 | M11: 0.285 | N11: 0.285 | O11: 0.285 | P11: 0.285 | Q11: 0.285 | R11: 0.285 | S11: =R11 -> 0.285 | T11: 0.285 | U11: 0.285 | V11: 0.285 | W11: 0.29
B12: Owner D | G12: 0 | H12: 0 | I12: 0 | J12: 0.06 | K12: 0.06 | L12: 0.06 | M12: 0.06 | N12: 0.06 | O12: 0.06 | P12: 0.06 | Q12: 0.06 | R12: 0.06 | S12: =R12 -> 0.06 | T12: 0.06 | U12: 0.06 | V12: 0.06 | W12: 0.03
B13: Owner E | G13: 0 | H13: 0 | I13: 0 | J13: 0 | K13: 0 | L13: 0 | M13: 0 | N13: 0 | O13: 0 | P13: 0 | Q13: 0 | R13: 0 | S13: =R13 -> 0 | T13: 0 | U13: 0 | V13: 0 | W13: 0
B15: Total Equity Ownership | G15: =SUM(G9:G13) -> 1 | H15: =SUM(H9:H13) -> 1 | I15: =SUM(I9:I13) -> 1 | J15: =SUM(J9:J13) -> 1 | K15: =SUM(K9:K13) -> 1 | L15: =SUM(L9:L13) -> 1 | M15: =SUM(M9:M13) -> 1 | N15: =SUM(N9:N13) -> 1 | ... W15: =SUM(W9:W13) -> 1
B18: Rate of Return on Invested Cash
B19: (Not currently built into model)
B21: ='Assumptions - Non-Personnel Exp'!B8 -> Technology Engineering & Development - Capitalized
B22: Additions (Fixed Assets) | G22: ='Assumptions - Non-Personnel Exp'!G13 -> 0 | H22: ='Assumptions - Non-Personnel Exp'!H13 -> 50000 | I22: ='Assumptions - Non-Personnel Exp'!I13 -> 50000 | J22: ='Assumptions - Non-Personnel Exp'!J13 -> 50000 | K22: ='Assumptions - Non-Personnel Exp'!K13 -> 50000 | L22: ='Assumptions - Non-Personnel Exp'!L13 -> 50000 | M22: ='Assumptions - Non-Personnel Exp'!M13 -> 50000 | N22: ='Assumptions - Non-Personnel Exp'!N13 -> 50000 | ... R22: ='Assumptions - Non-Personnel Exp'!R13 -> 0 | T22: ='Assumptions - Non-Personnel Exp'!T13 -> 150000 | U22: ='Assumptions - Non-Personnel Exp'!U13 -> 200000 | V22: ='Assumptions - Non-Personnel Exp'!V13 -> 100000 | W22: ='Assumptions - Non-Personnel Exp'!W13 -> 350000
B23: Cumulative Fixed Assets | G23: =G22 -> 0 | H23: =G23+H22 -> 50000 | I23: =H23+I22 -> 100000 | J23: =I23+J22 -> 150000 | K23: =J23+K22 -> 200000 | L23: =K23+L22 -> 250000 | M23: =L23+M22 -> 300000 | N23: =M23+N22 -> 350000 | O23: =N23+O22 -> 350000 | ... R23: =Q23+R22 -> 350000 | S23: =R23 -> 350000 | T23: =S23+T22 -> 500000 | U23: =T23+U22 -> 700000 | V23: =U23+V22 -> 800000 | W23: =V23+W22 -> 1150000
B25: Average Depreciable Life (years) | C25: 5
B26: 1/2 Year Convention in years 2-5
B28: Long-Term Borrowing | S28: =R28
B29: (Not currently built into model)
B30: Interest Rate on Long-Term Borrowing
B31: (Not currently built into model)
B33: Equity Investments
B34: Additions | G34: 350000 | H34: 0 | I34: 0 | J34: 0 | K34: 0 | L34: 0 | M34: 0 | N34: 0 | O34: 0 | P34: 0 | Q34: 0 | R34: 0 | S34: =SUM(G34:R34) -> 350000 | T34: 150000 | U34: 100000 | V34: 100000 | W34: 100000
B35: Withdrawals

Sheet Balance Sheets 
A2: Balance Sheets
A4: * Shaded assumptions can be edited | G4: Year 1
G5: Sept | H5: Oct | I5: Nov | J5: Dec | K5: Jan | L5: Feb | M5: Mar | N5: Apr | O5: May | P5: Jun | Q5: Jul | R5: Aug | S5: Year 1 | T5: Year 2 | U5: Year 3 | V5: Year 4 | W5: Year 5
B8: Assets:
B10: Cash & Investments | G10: ='Cash Flow Statements'!G28 -> 310114 | H10: ='Cash Flow Statements'!H28 -> 232228 | I10: ='Cash Flow Statements'!I28 -> 154842 | J10: ='Cash Flow Statements'!J28 -> 75456 | K10: ='Cash Flow Statements'!K28 -> -7930 | L10: ='Cash Flow Statements'!L28 -> -91316 | M10: ='Cash Flow Statements'!M28 -> -174702 | N10: ='Cash Flow Statements'!N28 -> -252238 | ... W10: ='Cash Flow Statements'!W28 -> 9131350
B12: Accounts Receivable
B14: Fixed Assets | G14: ='Assumpt.-Equity & Bal Sheet '!G23 -> 0 | H14: ='Assumpt.-Equity & Bal Sheet '!H23 -> 50000 | I14: ='Assumpt.-Equity & Bal Sheet '!I23 -> 100000 | J14: ='Assumpt.-Equity & Bal Sheet '!J23 -> 150000 | K14: ='Assumpt.-Equity & Bal Sheet '!K23 -> 200000 | L14: ='Assumpt.-Equity & Bal Sheet '!L23 -> 250000 | M14: ='Assumpt.-Equity & Bal Sheet '!M23 -> 300000 | N14: ='Assumpt.-Equity & Bal Sheet '!N23 -> 350000 | ... W14: ='Assumpt.-Equity & Bal Sheet '!W23 -> 1150000
B15: Accumulated Depreciation | G15: =-'Assumpt.-Equity & Bal Sheet '!G23/'Assumpt.-Equity & Bal Sheet '!$C$25/12 -> 0 | H15: =-('Assumpt.-Equity & Bal Sheet '!H23/'Assumpt.-Equity & Bal Sheet '!$C$25/12)+G15 -> -833.33333 | I15: =-('Assumpt.-Equity & Bal Sheet '!I23/'Assumpt.-Equity & Bal Sheet '!$C$25/12)+H15 -> -2500 | J15: =-('Assumpt.-Equity & Bal Sheet '!J23/'Assumpt.-Equity & Bal Sheet '!$C$25/12)+I15 -> -5000 | K15: =-('Assumpt.-Equity & Bal Sheet '!K23/'Assumpt.-Equity & Bal Sheet '!$C$25/12)+J15 -> -8333.3333 | L15: =-('Assumpt.-Equity & Bal Sheet '!L23/'Assumpt.-Equity & Bal Sheet '!$C$25/12)+K15 -> -12500 | M15: =-('Assumpt.-Equity & Bal Sheet '!M23/'Assumpt.-Equity & Bal Sheet '!$C$25/12)+L15 -> -17500 | N15: =-('Assumpt.-Equity & Bal Sheet '!N23/'Assumpt.-Equity & Bal Sheet '!$C$25/12)+M15 -> -23333.333 | O15: =-('Assumpt.-Equity & Bal Sheet '!O23/'Assumpt.-Equity & Bal Sheet '!$C$25/12)+N15 -> -29166.667 | ... R15: =-('Assumpt.-Equity & Bal Sheet '!R23/'Assumpt.-Equity & Bal Sheet '!$C$25/12)+Q15 -> -46666.667 | S15: =R15 -> -46666.667 | T15: =-('Assumpt.-Equity & Bal Sheet '!S23/'Assumpt.-Equity & Bal Sheet '!$C$25-(('Assumpt.-Equity & Bal Sheet '!T22/'Assumpt.-Equity & Bal Sheet '!$C$25)*0.5))+S15 -> -101666.67 | U15: =-('Assumpt.-Equity & Bal Sheet '!T23/'Assumpt.-Equity & Bal Sheet '!$C$25-(('Assumpt.-Equity & Bal Sheet '!U22/'Assumpt.-Equity & Bal Sheet '!$C$25)*0.5))+T15 -> -181666.67 | V15: =-('Assumpt.-Equity & Bal Sheet '!U23/'Assumpt.-Equity & Bal Sheet '!$C$25-(('Assumpt.-Equity & Bal Sheet '!V22/'Assumpt.-Equity & Bal Sheet '!$C$25)*0.5))+U15 -> -311666.67 | W15: =-('Assumpt.-Equity & Bal Sheet '!V23/'Assumpt.-Equity & Bal Sheet '!$C$25-(('Assumpt.-Equity & Bal Sheet '!W22/'Assumpt.-Equity & Bal Sheet '!$C$25)*0.5))+V15 -> -436666.67
B16: Fixed Assets (Net) | G16: =G14+G15 -> 0 | H16: =H14+H15 -> 49166.667 | I16: =I14+I15 -> 97500 | J16: =J14+J15 -> 145000 | K16: =K14+K15 -> 191666.67 | L16: =L14+L15 -> 237500 | M16: =M14+M15 -> 282500 | N16: =N14+N15 -> 326666.67 | ... W16: =W14+W15 -> 713333.33
B18: Total Assets | G18: =G16+G12+G10 -> 310114 | H18: =H16+H12+H10 -> 281394.67 | I18: =I16+I12+I10 -> 252342 | J18: =J16+J12+J10 -> 220456 | K18: =K16+K12+K10 -> 183736.67 | L18: =L16+L12+L10 -> 146184 | M18: =M16+M12+M10 -> 107798 | N18: =N16+N12+N10 -> 74428.667 | ... W18: =W16+W12+W10 -> 9844683.3
B21: Liabilities & Equity
B23: Accounts Payable
B24: Long-Term Debt
B26: Total Liabilities | G26: =G23+G24 -> 0 | H26: =H23+H24 -> 0 | I26: =I23+I24 -> 0 | J26: =J23+J24 -> 0 | K26: =K23+K24 -> 0 | L26: =L23+L24 -> 0 | M26: =M23+M24 -> 0 | N26: =N23+N24 -> 0 | ... W26: =W23+W24 -> 0
B29: Owner's Equity
B31: Owner A | G31: ='Assumpt.-Equity & Bal Sheet '!G9*'Balance Sheets '!G$37 -> 124045.6 | H31: ='Assumpt.-Equity & Bal Sheet '!H9*'Balance Sheets '!H$37 -> 112557.87 | I31: ='Assumpt.-Equity & Bal Sheet '!I9*'Balance Sheets '!I$37 -> 100936.8 | J31: ='Assumpt.-Equity & Bal Sheet '!J9*'Balance Sheets '!J$37 -> 81568.72 | K31: ='Assumpt.-Equity & Bal Sheet '!K9*'Balance Sheets '!K$37 -> 67982.567 | L31: ='Assumpt.-Equity & Bal Sheet '!L9*'Balance Sheets '!L$37 -> 54088.08 | M31: ='Assumpt.-Equity & Bal Sheet '!M9*'Balance Sheets '!M$37 -> 39885.26 | N31: ='Assumpt.-Equity & Bal Sheet '!N9*'Balance Sheets '!N$37 -> 27538.607 | ... W31: ='Assumpt.-Equity & Bal Sheet '!W9*'Balance Sheets '!W$37 -> 3839426.5
B32: Owner B | G32: ='Assumpt.-Equity & Bal Sheet '!G10*'Balance Sheets '!G$37 -> 93034.2 | H32: ='Assumpt.-Equity & Bal Sheet '!H10*'Balance Sheets '!H$37 -> 84418.4 | I32: ='Assumpt.-Equity & Bal Sheet '!I10*'Balance Sheets '!I$37 -> 75702.6 | J32: ='Assumpt.-Equity & Bal Sheet '!J10*'Balance Sheets '!J$37 -> 62829.96 | K32: ='Assumpt.-Equity & Bal Sheet '!K10*'Balance Sheets '!K$37 -> 52364.95 | L32: ='Assumpt.-Equity & Bal Sheet '!L10*'Balance Sheets '!L$37 -> 41662.44 | M32: ='Assumpt.-Equity & Bal Sheet '!M10*'Balance Sheets '!M$37 -> 30722.43 | N32: ='Assumpt.-Equity & Bal Sheet '!N10*'Balance Sheets '!N$37 -> 21212.17 | ... W32: ='Assumpt.-Equity & Bal Sheet '!W10*'Balance Sheets '!W$37 -> 2854958.2
B33: Owner C | G33: ='Assumpt.-Equity & Bal Sheet '!G11*'Balance Sheets '!G$37 -> 93034.2 | H33: ='Assumpt.-Equity & Bal Sheet '!H11*'Balance Sheets '!H$37 -> 84418.4 | I33: ='Assumpt.-Equity & Bal Sheet '!I11*'Balance Sheets '!I$37 -> 75702.6 | J33: ='Assumpt.-Equity & Bal Sheet '!J11*'Balance Sheets '!J$37 -> 62829.96 | K33: ='Assumpt.-Equity & Bal Sheet '!K11*'Balance Sheets '!K$37 -> 52364.95 | L33: ='Assumpt.-Equity & Bal Sheet '!L11*'Balance Sheets '!L$37 -> 41662.44 | M33: ='Assumpt.-Equity & Bal Sheet '!M11*'Balance Sheets '!M$37 -> 30722.43 | N33: ='Assumpt.-Equity & Bal Sheet '!N11*'Balance Sheets '!N$37 -> 21212.17 | ... W33: ='Assumpt.-Equity & Bal Sheet '!W11*'Balance Sheets '!W$37 -> 2854958.2
B34: Owner D | G34: ='Assumpt.-Equity & Bal Sheet '!G12*'Balance Sheets '!G$37 -> 0 | H34: ='Assumpt.-Equity & Bal Sheet '!H12*'Balance Sheets '!H$37 -> 0 | I34: ='Assumpt.-Equity & Bal Sheet '!I12*'Balance Sheets '!I$37 -> 0 | J34: ='Assumpt.-Equity & Bal Sheet '!J12*'Balance Sheets '!J$37 -> 13227.36 | K34: ='Assumpt.-Equity & Bal Sheet '!K12*'Balance Sheets '!K$37 -> 11024.2 | L34: ='Assumpt.-Equity & Bal Sheet '!L12*'Balance Sheets '!L$37 -> 8771.04 | M34: ='Assumpt.-Equity & Bal Sheet '!M12*'Balance Sheets '!M$37 -> 6467.88 | N34: ='Assumpt.-Equity & Bal Sheet '!N12*'Balance Sheets '!N$37 -> 4465.72 | ... W34: ='Assumpt.-Equity & Bal Sheet '!W12*'Balance Sheets '!W$37 -> 295340.5
B35: Owner E | G35: ='Assumpt.-Equity & Bal Sheet '!G13*'Balance Sheets '!G$37 -> 0 | H35: ='Assumpt.-Equity & Bal Sheet '!H13*'Balance Sheets '!H$37 -> 0 | I35: ='Assumpt.-Equity & Bal Sheet '!I13*'Balance Sheets '!I$37 -> 0 | J35: ='Assumpt.-Equity & Bal Sheet '!J13*'Balance Sheets '!J$37 -> 0 | K35: ='Assumpt.-Equity & Bal Sheet '!K13*'Balance Sheets '!K$37 -> 0 | L35: ='Assumpt.-Equity & Bal Sheet '!L13*'Balance Sheets '!L$37 -> 0 | M35: ='Assumpt.-Equity & Bal Sheet '!M13*'Balance Sheets '!M$37 -> 0 | N35: ='Assumpt.-Equity & Bal Sheet '!N13*'Balance Sheets '!N$37 -> 0 | ... W35: ='Assumpt.-Equity & Bal Sheet '!W13*'Balance Sheets '!W$37 -> 0
B37: Total Owner's Equity | G37: =G39-G26 -> 310114 | H37: =H39-H26 -> 281394.67 | I37: =I39-I26 -> 252342 | J37: =J39-J26 -> 220456 | K37: =K39-K26 -> 183736.67 | L37: =L39-L26 -> 146184 | M37: =M39-M26 -> 107798 | N37: =N39-N26 -> 74428.667 | ... W37: =W39-W26 -> 9844683.3
B39: Total Liabilities and Owner's Equity | G39: =G18 -> 310114 | H39: =H18 -> 281394.67 | I39: =I18 -> 252342 | J39: =J18 -> 220456 | K39: =K18 -> 183736.67 | L39: =L18 -> 146184 | M39: =M18 -> 107798 | N39: =N18 -> 74428.667 | ... W39: =W18 -> 9844683.3

Sheet Income Statements
A2: Income Statements
A4: * Shaded assumptions can be edited | G4: Year 1 Ramp Up
G5: Sept | H5: Oct | I5: Nov | J5: Dec | K5: Jan | L5: Feb | M5: Mar | N5: Apr | O5: May | P5: Jun | Q5: Jul | R5: Aug | S5: Year 1 | T5: Year 2 | U5: Year 3 | V5: Year 4 | W5: Year 5
B7: Operating Revenue:
B9: Individual License | G9: ='Assumptions - Revenue'!$E34*'Assumptions - Revenue'!G7 -> 0 | H9: ='Assumptions - Revenue'!$E34*'Assumptions - Revenue'!H7 -> 0 | I9: ='Assumptions - Revenue'!$E34*'Assumptions - Revenue'!I7 -> 0 | J9: ='Assumptions - Revenue'!$E34*'Assumptions - Revenue'!J7 -> 0 | K9: ='Assumptions - Revenue'!$E34*'Assumptions - Revenue'!K7 -> 0 | L9: ='Assumptions - Revenue'!$E34*'Assumptions - Revenue'!L7 -> 0 | M9: ='Assumptions - Revenue'!$E34*'Assumptions - Revenue'!M7 -> 0 | N9: ='Assumptions - Revenue'!$E34*'Assumptions - Revenue'!N7 -> 3500 | ... R9: ='Assumptions - Revenue'!$E34*'Assumptions - Revenue'!R7 -> 45000 | S9: =SUM(G9:R9) -> 113500 | T9: ='Assumptions - Revenue'!F34*'Assumptions - Revenue'!T7*12 -> 960000 | U9: ='Assumptions - Revenue'!G34*'Assumptions - Revenue'!U7*12 -> 1320000 | V9: ='Assumptions - Revenue'!H34*'Assumptions - Revenue'!V7*12 -> 1650000 | W9: ='Assumptions - Revenue'!I34*'Assumptions - Revenue'!W7*12 -> 2178000
B10: Individual Plus Five Licenses | G10: ='Assumptions - Revenue'!$E35*'Assumptions - Revenue'!G8 -> 0 | H10: ='Assumptions - Revenue'!$E35*'Assumptions - Revenue'!H8 -> 0 | I10: ='Assumptions - Revenue'!$E35*'Assumptions - Revenue'!I8 -> 0 | J10: ='Assumptions - Revenue'!$E35*'Assumptions - Revenue'!J8 -> 0 | K10: ='Assumptions - Revenue'!$E35*'Assumptions - Revenue'!K8 -> 0 | L10: ='Assumptions - Revenue'!$E35*'Assumptions - Revenue'!L8 -> 0 | M10: ='Assumptions - Revenue'!$E35*'Assumptions - Revenue'!M8 -> 0 | N10: ='Assumptions - Revenue'!$E35*'Assumptions - Revenue'!N8 -> 1750 | ... R10: ='Assumptions - Revenue'!$E35*'Assumptions - Revenue'!R8 -> 17500 | S10: =SUM(G10:R10) -> 37800 | T10: ='Assumptions - Revenue'!F35*'Assumptions - Revenue'!T8*12 -> 420000 | U10: ='Assumptions - Revenue'!G35*'Assumptions - Revenue'!U8*12 -> 646800 | V10: ='Assumptions - Revenue'!H35*'Assumptions - Revenue'!V8*12 -> 693000 | W10: ='Assumptions - Revenue'!I35*'Assumptions - Revenue'!W8*12 -> 1778700
B11: Individual Plus Ten Licenses | G11: ='Assumptions - Revenue'!$E36*'Assumptions - Revenue'!G9 -> 0 | H11: ='Assumptions - Revenue'!$E36*'Assumptions - Revenue'!H9 -> 0 | I11: ='Assumptions - Revenue'!$E36*'Assumptions - Revenue'!I9 -> 0 | J11: ='Assumptions - Revenue'!$E36*'Assumptions - Revenue'!J9 -> 0 | K11: ='Assumptions - Revenue'!$E36*'Assumptions - Revenue'!K9 -> 0 | L11: ='Assumptions - Revenue'!$E36*'Assumptions - Revenue'!L9 -> 0 | M11: ='Assumptions - Revenue'!$E36*'Assumptions - Revenue'!M9 -> 0 | N11: ='Assumptions - Revenue'!$E36*'Assumptions - Revenue'!N9 -> 600 | ... R11: ='Assumptions - Revenue'!$E36*'Assumptions - Revenue'!R9 -> 15000 | S11: =SUM(G11:R11) -> 32400 | T11: ='Assumptions - Revenue'!F36*'Assumptions - Revenue'!T9*12 -> 216000 | U11: ='Assumptions - Revenue'!G36*'Assumptions - Revenue'!U9*12 -> 316800 | V11: ='Assumptions - Revenue'!H36*'Assumptions - Revenue'!V9*12 -> 594000 | W11: ='Assumptions - Revenue'!I36*'Assumptions - Revenue'!W9*12 -> 871200
B12: Unlimited | G12: ='Assumptions - Revenue'!$E37*'Assumptions - Revenue'!G10 -> 0 | H12: ='Assumptions - Revenue'!$E37*'Assumptions - Revenue'!H10 -> 0 | I12: ='Assumptions - Revenue'!$E37*'Assumptions - Revenue'!I10 -> 0 | J12: ='Assumptions - Revenue'!$E37*'Assumptions - Revenue'!J10 -> 0 | K12: ='Assumptions - Revenue'!$E37*'Assumptions - Revenue'!K10 -> 0 | L12: ='Assumptions - Revenue'!$E37*'Assumptions - Revenue'!L10 -> 0 | M12: ='Assumptions - Revenue'!$E37*'Assumptions - Revenue'!M10 -> 0 | N12: ='Assumptions - Revenue'!$E37*'Assumptions - Revenue'!N10 -> 0 | ... R12: ='Assumptions - Revenue'!$E37*'Assumptions - Revenue'!R10 -> 10000 | S12: =SUM(G12:R12) -> 21250 | T12: ='Assumptions - Revenue'!F37*'Assumptions - Revenue'!T10*12 -> 150000 | U12: ='Assumptions - Revenue'!G37*'Assumptions - Revenue'!U10*12 -> 198000 | V12: ='Assumptions - Revenue'!H37*'Assumptions - Revenue'!V10*12 -> 495000 | W12: ='Assumptions - Revenue'!I37*'Assumptions - Revenue'!W10*12 -> 907500
B14: Total Subscription Revenue | G14: =SUM(G9:G12) -> 0 | H14: =SUM(H9:H12) -> 0 | I14: =SUM(I9:I12) -> 0 | J14: =SUM(J9:J12) -> 0 | K14: =SUM(K9:K12) -> 0 | L14: =SUM(L9:L12) -> 0 | M14: =SUM(M9:M12) -> 0 | N14: =SUM(N9:N12) -> 5850 | ... W14: =SUM(W9:W12) -> 5735400
B16: Other Operating Revenue
B18: Total Operating Revenue | G18: =G14+G16 -> 0 | H18: =H14+H16 -> 0 | I18: =I14+I16 -> 0 | J18: =J14+J16 -> 0 | K18: =K14+K16 -> 0 | L18: =L14+L16 -> 0 | M18: =M14+M16 -> 0 | N18: =N14+N16 -> 5850 | ... W18: =W14+W16 -> 5735400
B20: Operating Expenses:
B22: Employee Salary Expense | G22: ='Assumptions - Personnel'!G22 -> 16250 | H22: ='Assumptions - Personnel'!H22 -> 16250 | I22: ='Assumptions - Personnel'!I22 -> 16250 | J22: ='Assumptions - Personnel'!J22 -> 16250 | K22: ='Assumptions - Personnel'!K22 -> 16250 | L22: ='Assumptions - Personnel'!L22 -> 16250 | M22: ='Assumptions - Personnel'!M22 -> 16250 | N22: ='Assumptions - Personnel'!N22 -> 16250 | ... W22: ='Assumptions - Personnel'!W22 -> 550000
B23: Employee Benefits | G23: ='Assumptions - Personnel'!G22*'Assumptions - Personnel'!$C$25 -> 3575 | H23: ='Assumptions - Personnel'!H22*'Assumptions - Personnel'!$C$25 -> 3575 | I23: ='Assumptions - Personnel'!I22*'Assumptions - Personnel'!$C$25 -> 3575 | J23: ='Assumptions - Personnel'!J22*'Assumptions - Personnel'!$C$25 -> 3575 | K23: ='Assumptions - Personnel'!K22*'Assumptions - Personnel'!$C$25 -> 3575 | L23: ='Assumptions - Personnel'!L22*'Assumptions - Personnel'!$C$25 -> 3575 | M23: ='Assumptions - Personnel'!M22*'Assumptions - Personnel'!$C$25 -> 3575 | N23: ='Assumptions - Personnel'!N22*'Assumptions - Personnel'!$C$25 -> 3575 | ... W23: ='Assumptions - Personnel'!W22*'Assumptions - Personnel'!$C$25 -> 121000
B24: Contract Labor | G24: ='Assumptions - Personnel'!G12 -> 4166 | H24: ='Assumptions - Personnel'!H12 -> 4166 | I24: ='Assumptions - Personnel'!I12 -> 4166 | J24: ='Assumptions - Personnel'!J12 -> 4166 | K24: ='Assumptions - Personnel'!K12 -> 4166 | L24: ='Assumptions - Personnel'!L12 -> 4166 | M24: ='Assumptions - Personnel'!M12 -> 4166 | N24: ='Assumptions - Personnel'!N12 -> 4166 | ... W24: ='Assumptions - Personnel'!W12 -> 350000
B25: Marketing/Advertising | G25: ='Assumptions - Non-Personnel Exp'!G18 -> 0 | H25: ='Assumptions - Non-Personnel Exp'!H18 -> 0 | I25: ='Assumptions - Non-Personnel Exp'!I18 -> 2500 | J25: ='Assumptions - Non-Personnel Exp'!J18 -> 4500 | K25: ='Assumptions - Non-Personnel Exp'!K18 -> 8500 | L25: ='Assumptions - Non-Personnel Exp'!L18 -> 8500 | M25: ='Assumptions - Non-Personnel Exp'!M18 -> 8500 | N25: ='Assumptions - Non-Personnel Exp'!N18 -> 8500 | ... W25: ='Assumptions - Non-Personnel Exp'!W18 -> 150000
B26: Website Hosting, AWS Database, Misc Saas Fees | G26: ='Assumptions - Non-Personnel Exp'!G21 -> 845 | H26: ='Assumptions - Non-Personnel Exp'!H21 -> 845 | I26: ='Assumptions - Non-Personnel Exp'!I21 -> 845 | J26: ='Assumptions - Non-Personnel Exp'!J21 -> 845 | K26: ='Assumptions - Non-Personnel Exp'!K21 -> 845 | L26: ='Assumptions - Non-Personnel Exp'!L21 -> 845 | M26: ='Assumptions - Non-Personnel Exp'!M21 -> 845 | N26: ='Assumptions - Non-Personnel Exp'!N21 -> 845 | ... W26: ='Assumptions - Non-Personnel Exp'!W21 -> 10140
B27: Other Expense (Legal, CRM, Travel) | G27: ='Assumptions - Non-Personnel Exp'!G30 -> 15050 | H27: ='Assumptions - Non-Personnel Exp'!H30 -> 3050 | I27: ='Assumptions - Non-Personnel Exp'!I30 -> 50 | J27: ='Assumptions - Non-Personnel Exp'!J30 -> 50 | K27: ='Assumptions - Non-Personnel Exp'!K30 -> 50 | L27: ='Assumptions - Non-Personnel Exp'!L30 -> 50 | M27: ='Assumptions - Non-Personnel Exp'!M30 -> 50 | N27: ='Assumptions - Non-Personnel Exp'!N30 -> 50 | ... W27: ='Assumptions - Non-Personnel Exp'!W30 -> 25600
B28: Technology Maintenance | G28: ='Assumptions - Non-Personnel Exp'!G15 | H28: ='Assumptions - Non-Personnel Exp'!H15 | I28: ='Assumptions - Non-Personnel Exp'!I15 | J28: ='Assumptions - Non-Personnel Exp'!J15 | K28: ='Assumptions - Non-Personnel Exp'!K15 | L28: ='Assumptions - Non-Personnel Exp'!L15 | M28: ='Assumptions - Non-Personnel Exp'!M15 | N28: ='Assumptions - Non-Personnel Exp'!N15 | ... W28: ='Assumptions - Non-Personnel Exp'!W15
B29: Depreciation | G29: =-'Balance Sheets '!G15 -> 0 | H29: =-'Balance Sheets '!H15+'Balance Sheets '!G15 -> 833.33333 | I29: =-'Balance Sheets '!I15+'Balance Sheets '!H15 -> 1666.6667 | J29: =-'Balance Sheets '!J15+'Balance Sheets '!I15 -> 2500 | K29: =-'Balance Sheets '!K15+'Balance Sheets '!J15 -> 3333.3333 | L29: =-'Balance Sheets '!L15+'Balance Sheets '!K15 -> 4166.6667 | M29: =-'Balance Sheets '!M15+'Balance Sheets '!L15 -> 5000 | N29: =-'Balance Sheets '!N15+'Balance Sheets '!M15 -> 5833.3333 | O29: =-'Balance Sheets '!O15+'Balance Sheets '!N15 -> 5833.3333 | ... R29: =-'Balance Sheets '!R15+'Balance Sheets '!Q15 -> 5833.3333 | S29: =SUM(G29:R29) -> 46666.667 | T29: =-'Balance Sheets '!T15+'Balance Sheets '!S15 -> 55000 | U29: =-'Balance Sheets '!U15+'Balance Sheets '!T15 -> 80000 | V29: =-'Balance Sheets '!V15+'Balance Sheets '!U15 -> 130000 | W29: =-'Balance Sheets '!W15+'Balance Sheets '!V15 -> 125000
B31: Total Operating Expenses | G31: =SUM(G21:G29) -> 39886 | H31: =SUM(H21:H29) -> 28719.333 | I31: =SUM(I21:I29) -> 29052.667 | J31: =SUM(J21:J29) -> 31886 | K31: =SUM(K21:K29) -> 36719.333 | L31: =SUM(L21:L29) -> 37552.667 | M31: =SUM(M21:M29) -> 38386 | N31: =SUM(N21:N29) -> 39219.333 | ... W31: =SUM(W21:W29) -> 1331740
B33: Excess (Deficit) Revenue Over Expenses | G33: =G18-G31 -> -39886 | H33: =H18-H31 -> -28719.333 | I33: =I18-I31 -> -29052.667 | J33: =J18-J31 -> -31886 | K33: =K18-K31 -> -36719.333 | L33: =L18-L31 -> -37552.667 | M33: =M18-M31 -> -38386 | N33: =N18-N31 -> -33369.333 | ... W33: =W18-W31 -> 4403660

Sheet Cash Flow Statements
A2: Cash Flow Statements
A4: * Shaded assumptions can be edited | G4: Year 1 Ramp Up
G5: Sept | H5: Oct | I5: Nov | J5: Dec | K5: Jan | L5: Feb | M5: Mar | N5: Apr | O5: May | P5: Jun | Q5: Jul | R5: Aug | S5: Year 1 | T5: Year 2 | U5: Year 3 | V5: Year 4 | W5: Year 5
B7: Excess (Deficit) Revenue Over Expenses | G7: ='Income Statements'!G33 -> -39886 | H7: ='Income Statements'!H33 -> -28719.333 | I7: ='Income Statements'!I33 -> -29052.667 | J7: ='Income Statements'!J33 -> -31886 | K7: ='Income Statements'!K33 -> -36719.333 | L7: ='Income Statements'!L33 -> -37552.667 | M7: ='Income Statements'!M33 -> -38386 | N7: ='Income Statements'!N33 -> -33369.333 | ... W7: ='Income Statements'!W33 -> 4403660
B9: Add Back Depreciation | G9: ='Income Statements'!G29 -> 0 | H9: ='Income Statements'!H29 -> 833.33333 | I9: ='Income Statements'!I29 -> 1666.6667 | J9: ='Income Statements'!J29 -> 2500 | K9: ='Income Statements'!K29 -> 3333.3333 | L9: ='Income Statements'!L29 -> 4166.6667 | M9: ='Income Statements'!M29 -> 5000 | N9: ='Income Statements'!N29 -> 5833.3333 | ... W9: ='Income Statements'!W29 -> 125000
B11: Operating Cash Flow | G11: =G7+G9 -> -39886 | H11: =H7+H9 -> -27886 | I11: =I7+I9 -> -27386 | J11: =J7+J9 -> -29386 | K11: =K7+K9 -> -33386 | L11: =L7+L9 -> -33386 | M11: =M7+M9 -> -33386 | N11: =N7+N9 -> -27536 | ... W11: =W7+W9 -> 4528660
B13: Sources of Cash:
B15: Equity Investments - Additions | G15: ='Assumpt.-Equity & Bal Sheet '!G34 -> 350000 | H15: ='Assumpt.-Equity & Bal Sheet '!H34 -> 0 | I15: ='Assumpt.-Equity & Bal Sheet '!I34 -> 0 | J15: ='Assumpt.-Equity & Bal Sheet '!J34 -> 0 | K15: ='Assumpt.-Equity & Bal Sheet '!K34 -> 0 | L15: ='Assumpt.-Equity & Bal Sheet '!L34 -> 0 | M15: ='Assumpt.-Equity & Bal Sheet '!M34 -> 0 | N15: ='Assumpt.-Equity & Bal Sheet '!N34 -> 0 | ... W15: ='Assumpt.-Equity & Bal Sheet '!W34 -> 100000
B18: Uses of Cash:
B20: Fixed Asset Purchases | G20: =-'Assumptions - Non-Personnel Exp'!G13 -> 0 | H20: =-'Assumptions - Non-Personnel Exp'!H13 -> -50000 | I20: =-'Assumptions - Non-Personnel Exp'!I13 -> -50000 | J20: =-'Assumptions - Non-Personnel Exp'!J13 -> -50000 | K20: =-'Assumptions - Non-Personnel Exp'!K13 -> -50000 | L20: =-'Assumptions - Non-Personnel Exp'!L13 -> -50000 | M20: =-'Assumptions - Non-Personnel Exp'!M13 -> -50000 | N20: =-'Assumptions - Non-Personnel Exp'!N13 -> -50000 | ... W20: =-'Assumptions - Non-Personnel Exp'!W13 -> -350000
B24: Change in Cash | G24: =SUM(G11:G22) -> 310114 | H24: =SUM(H11:H22) -> -77886 | I24: =SUM(I11:I22) -> -77386 | J24: =SUM(J11:J22) -> -79386 | K24: =SUM(K11:K22) -> -83386 | L24: =SUM(L11:L22) -> -83386 | M24: =SUM(M11:M22) -> -83386 | N24: =SUM(N11:N22) -> -77536 | ... W24: =SUM(W11:W22) -> 4278660
B26: Cash at Beginning of Period | G26: =F28 | H26: =G28 -> 310114 | I26: =H28 -> 232228 | J26: =I28 -> 154842 | K26: =J28 -> 75456 | L26: =K28 -> -7930 | M26: =L28 -> -91316 | N26: =M28 -> -174702 | ... R26: =Q28 -> -243796 | S26: 0 | T26: =S28 -> -190690 | U26: =T28 -> 913070 | V26: =U28 -> 2435930 | W26: =V28 -> 4852690
B28: Cash at End of Period | G28: =G24+G26 -> 310114 | H28: =H24+H26 -> 232228 | I28: =I24+I26 -> 154842 | J28: =J24+J26 -> 75456 | K28: =K24+K26 -> -7930 | L28: =L24+L26 -> -91316 | M28: =M24+M26 -> -174702 | N28: =N24+N26 -> -252238 | ... W28: =W24+W26 -> 9131350
